MANIFEST.in
README.md
setup.py
amio/__init__.py
amio/audio_clip.c
amio/audio_clip.h
amio/audio_clip.py
amio/communication.c
amio/communication.h
amio/driver.h
amio/dummy_interface.py
amio/fader.py
amio/gc.c
amio/gc.h
amio/input_chunk.c
amio/input_chunk.h
amio/interface.c
amio/interface.h
amio/interface.py
amio/jack_driver.c
amio/jack_driver.h
amio/mixer.c
amio/mixer.h
amio/native.i
amio/native.py
amio/native_interface.py
amio/null_interface.py
amio/pa_memorybarrier.h
amio/pa_ringbuffer.c
amio/pa_ringbuffer.h
amio/playspec.c
amio/playspec.h
amio/playspec.py
amio/pool.c
amio/pool.h
amio.egg-info/PKG-INFO
amio.egg-info/SOURCES.txt
amio.egg-info/dependency_links.txt
amio.egg-info/requires.txt
amio.egg-info/top_level.txt